twist/TwistAPI.py
twist/TwistCbShutter.py
twist/TwistDevice.py
twist/TwistLight.py
twist/TwistLouvre.py
twist/TwistModel.py
twist/TwistRgb.py
twist/TwistSensor.py
twist/TwistTypes.py
twist/Variants.py
twist/__init__.py
twist_innovation_api-0.0.3.dist-info/licenses/LICENSE
twist_innovation_api-0.0.3.dist-info/METADATA
twist_innovation_api-0.0.3.dist-info/WHEEL
twist_innovation_api-0.0.3.dist-info/top_level.txt
twist_innovation_api-0.0.3.dist-info/RECORD
