Metadata-Version: 2.4
Name: twist-innovation-api
Version: 0.0.3
Summary: Python library to talk to the twist-innovation api
Home-page: https://github.com/twist-innovation/twist-innovation-api
Author: Sibrecht Goudsmedt
Author-email: sibrecht.goudsmedt@twist-innovation.com
Classifier: Programming Language :: Python :: 3
Classifier: License :: OSI Approved :: GNU General Public License v3 (GPLv3)
Classifier: Operating System :: OS Independent
Requires-Python: >=3.7
License-File: LICENSE
Dynamic: author
Dynamic: author-email
Dynamic: classifier
Dynamic: description
Dynamic: description-content-type
Dynamic: home-page
Dynamic: license-file
Dynamic: requires-python
Dynamic: summary
